{
    "actionOnStepFail": null, 
    "enabled": true, 
    "externalUuid4": "b37f90d4-150f-41b1-a006-be798001d7ec", 
    "interpreter": 2, 
    "interpreterCommand": null, 
    "interpreterScriptExt": null, 
    "interpreterScriptSyntax": "powershell", 
    "key": "downloadinstallerformicrosoftpowertoys", 
    "name": "Download Installer for Microsoft PowerToys", 
    "osCredKey": "windowsuseradministrator", 
    "serverKey": "powertoysnode", 
    "successExitCode": 0, 
    "timeout": null, 
    "type": "com.servertribe.attune.tuples.StepWinRmTuple"
}